ides/__init__.py
ides/__main__.py
ides/api.py
ides-2022.6.15.1.dist-info/METADATA
ides-2022.6.15.1.dist-info/WHEEL
ides-2022.6.15.1.dist-info/top_level.txt
ides-2022.6.15.1.dist-info/RECORD
