Metadata-Version: 2.1
Name: ides
Version: 2022.6.15.1
Summary: Presenting with Jupyter
Author-email: Moshe Zadka <moshez@example.com>
License: Permission is hereby granted, free of charge, to any person obtaining a
Project-URL: Homepage, https://github.com/moshez/ides
